confocal/__init__.py
confocal/config.py
confocal/sources.py
confocal/utils.py
confocal-0.1.4.dist-info/METADATA
confocal-0.1.4.dist-info/WHEEL
confocal-0.1.4.dist-info/RECORD
