Metadata-Version: 2.4
Name: confocal
Version: 0.1.4
Summary: Multi-layer configuration management with source tracking
Project-URL: Homepage, https://github.com/joshuafcole/confocal
Project-URL: Repository, https://github.com/joshuafcole/confocal
Author-email: Your Name <your.email@example.com>
License: MIT
Requires-Python: >=3.8
Requires-Dist: pydantic-settings<2.11.0,>=2.0.0
Requires-Dist: pydantic<2.12.0,>=2.0.0
Requires-Dist: pyyaml>=6.0.0
Requires-Dist: rich>=13.0.0
Provides-Extra: dev
Requires-Dist: build>=0.10.0; extra == 'dev'
Requires-Dist: pytest>=7.0.0; extra == 'dev'
Requires-Dist: twine>=4.0.0; extra == 'dev'
